setup.py
zser/__init__.py
zser/decoder.py
zser/exceptions.py
zser/object.py
zser/parser.py
zser/varint.py
zser.egg-info/PKG-INFO
zser.egg-info/SOURCES.txt
zser.egg-info/dependency_links.txt
zser.egg-info/not-zip-safe
zser.egg-info/top_level.txt