Metadata-Version: 1.1
Name: zser
Version: 0.0.1
Summary: zcred serialization format
Home-page: https://github.com/zcred/zser
Author: Tony Arcieri
Author-email: bascule@gmail.com
License: MIT license
Keywords: authentication,cryptography,security,serialization,merkle
Platform: UNKNOWN
Classifier: Development Status :: 2 - Pre-Alpha
Classifier: Intended Audience :: Developers
Classifier: License :: OSI Approved :: MIT License
Classifier: Natural Language :: English
